pream_team/__init__.py
pream_team/__main__.py
pream_team/cache_manager.py
pream_team/github_pr_fetcher.py
pream_team/pream_team_app.py
pream_team/pream_team_ui.py
pream_team-1.3.0.dist-info/METADATA
pream_team-1.3.0.dist-info/WHEEL
pream_team-1.3.0.dist-info/entry_points.txt
pream_team-1.3.0.dist-info/licenses/LICENSE
pream_team-1.3.0.dist-info/RECORD
