Metadata-Version: 2.1
Name: pream-team
Version: 1.3.0
Summary: PReam-Team is a TUI utility that lists out open GitHub PRs for your team.
Project-URL: Homepage, https://github.com/nikoladucak/pream-team
Project-URL: Issues, https://github.com/nikoladucak/pream-team
Author-email: Nikola Dućak <nikola.duca@gmail.com>
License-File: LICENSE
Classifier: License :: OSI Approved :: MIT License
Classifier: Operating System :: OS Independent
Classifier: Programming Language :: Python :: 3
Requires-Python: >=3.8
Requires-Dist: aiohttp>=3.7.4
Requires-Dist: pyyaml>=5.4
Requires-Dist: urwid>=2.1.2
